amiimporter/AWSUtilities.py
amiimporter/__init__.py
amiimporter/amiupload.py
amiuploader-1.0.0.data/scripts/amiupload
amiuploader-1.0.0.dist-info/DESCRIPTION.rst
amiuploader-1.0.0.dist-info/METADATA
amiuploader-1.0.0.dist-info/RECORD
amiuploader-1.0.0.dist-info/WHEEL
amiuploader-1.0.0.dist-info/metadata.json
amiuploader-1.0.0.dist-info/top_level.txt
